folderobserver/README.md
folderobserver/__init__.py
folderobserver/requirements.txt
folderobserver/thirdparty.json
folderobserver-0.11.dist-info/LICENSE.rst
folderobserver-0.11.dist-info/METADATA
folderobserver-0.11.dist-info/WHEEL
folderobserver-0.11.dist-info/top_level.txt
folderobserver-0.11.dist-info/RECORD
