Metadata-Version: 2.1
Name: folderobserver
Version: 0.11
Summary: monitors and collects temporary files that might be created during software execution or system processes
Home-page: https://github.com/hansalemaos/folderobserver
Author: Johannes Fischer
Author-email: aulasparticularesdealemaosp@gmail.com
License: MIT
Keywords: temp,observer,files
Classifier: Development Status :: 4 - Beta
Classifier: Programming Language :: Python :: 3 :: Only
Classifier: Programming Language :: Python :: 3.10
Classifier: Topic :: Software Development :: Libraries :: Python Modules
Classifier: Topic :: Utilities
License-File: LICENSE.rst
Requires-Dist: a-pandas-ex-df-to-string
Requires-Dist: a-pandas-ex-set
Requires-Dist: copytool
Requires-Dist: get-file-type
Requires-Dist: hackycfgparser
Requires-Dist: kthread-sleep
Requires-Dist: pandas
Requires-Dist: remtmp
Requires-Dist: subprocesskiller
Requires-Dist: touchtouch
Requires-Dist: tqdm
Requires-Dist: uffspd
